{
  "TranslationProperties": {
    "Name": "server.items.Ore_Mithril_Basalt.name"
  },
  "Parent": "Ore_Mithril_Stone",
  "BlockType": {
    "Gathering": {
      "Breaking": {
        "GatherType": "Rocks",
        "DropList": {
          "Container": {
            "Type": "Multiple",
            "Containers": [
              {
                "Type": "Single",
                "Item": {
                  "ItemId": "Ore_Mithril"
                }
              },
              {
                "Type": "Single",
                "Item": {
                  "ItemId": "Rock_Basalt_Cobble"
                }
              }
            ]
          }
        }
      }
    },
    "Textures": [
      {
        "Weight": 1,
        "All": "BlockTextures/Rock_Basalt.png"
      }
    ],
    "ParticleColor": "#d2efec",
    "BlockParticleSetId": "Ore"
  },
  "Icon": "Icons/ItemsGenerated/Ore_Mithril_Basalt.png",
  "IconProperties": {
    "Scale": 0.58823,
    "Rotation": [
      22.5,
      45.0,
      22.5
    ],
    "Translation": [
      0.0,
      -13.5
    ]
  }
}
