{
  "Type": "Variant",
  "Reference": "BlankTemplate",
  "Modify": {
    "Appearance": "Boat",
    "MotionControllerList": [
      {
        "Type": "Walk",
        "MaxWalkSpeed": 6,
        "Gravity": 2,
        "MaxFallSpeed": 4,
        "Acceleration": 5
      }
    ],
    "MaxHealth": 100,
    "IsMountable": true,
    "MountAnchorX": 0,
    "MountAnchorY": 0.6,
    "MountAnchorZ": 0,
    "NameTranslationKey": {
      "Compute": "NameTranslationKey"
    }
  },
  "Parameters": {
    "NameTranslationKey": {
      "Value": "server.npcRoles.Wood_Boat.name",
      "Description": "Translation key for NPC name display"
    }
  }
}
